bcselector/__init__.py
bcselector/data_generation.py
bcselector/datasets.py
bcselector/run_tests.py
bcselector/variable_selection.py
bcselector/data/__init__.py
bcselector/data/hepatitis/__init__.py
bcselector/data/hepatitis/hepatitis.csv
bcselector/data/hepatitis/hepatitis_costs.json
bcselector/data/hepatitis/hepatitis_target.csv
bcselector/data/mimic3/__init__.py
bcselector/data/mimic3/mimic3.csv
bcselector/data/mimic3/mimic3_costs.json
bcselector/data/mimic3/mimic3_targets.csv
bcselector/data/sample_data/sample_costs.json
bcselector/data/sample_data/sample_data.csv
bcselector/data/sample_data/sample_target.csv
bcselector/filter_methods/__init__.py
bcselector/filter_methods/cost_based_filter_methods.py
bcselector/filter_methods/no_cost_based_filter_methods.py
bcselector/information_theory/__init__.py
bcselector/information_theory/basic_approximations.py
bcselector/information_theory/j_criterion_approximations.py
bcselector/tests/__init__.py
bcselector/tests/basic_information_theory_test.py
bcselector/tests/budget_loop_break_test.py
bcselector/tests/cost_based_filter_methods_test.py
bcselector/tests/data_generation_test.py
bcselector/tests/hyperparameter_selection_test.py
bcselector/tests/j_criterion_approximations_test.py
bcselector/tests/loading_data_test.py
bcselector/tests/no_cost_based_filter_methods_test.py
bcselector/tests/variable_selection_generated_data_test.py
bcselector/tests/variable_selection_test.py
bcselector-0.0.42.dist-info/LICENSE
bcselector-0.0.42.dist-info/METADATA
bcselector-0.0.42.dist-info/WHEEL
bcselector-0.0.42.dist-info/top_level.txt
bcselector-0.0.42.dist-info/RECORD
