Metadata-Version: 2.1
Name: bcselector
Version: 0.0.42
Summary: Python package to help you in variable selection.
Home-page: https://github.com/Kaketo/bcselector
Author: Tomasz Klonecki
Author-email: tomasz.klonecki@gmail.com
License: MIT
Classifier: Programming Language :: Python :: 3
Classifier: License :: OSI Approved :: MIT License
Classifier: Operating System :: OS Independent
Requires-Python: >=3.7
License-File: LICENSE
Requires-Dist: numpy (>=1.18.1)
Requires-Dist: matplotlib (>=3.2.1)
Requires-Dist: pandas (>=1.0.3)
Requires-Dist: scikit-learn (>=0.20.1)
Requires-Dist: tqdm (>=4.42.1)
Requires-Dist: pyitlib (>=0.2.2)
Requires-Dist: adjustText (==0.7.3)
